{
    "id":  "case_1057_b",
    "sfx":  "Assets/audio/node_paper_crunch.wav",
    "text":  [
                 "story.case_1057_b.0",
                 "story.case_1057_b.1",
                 "story.case_1057_b.2"
             ],
    "choices":  [
                    {
                        "text":  "story.common.next_case",
                        "next":  "day16_end"
                    }
                ],
    "effects":  [
                    {
                        "type":  "case_record",
                        "key":  "case_1057",
                        "title":  "story.case_1057.0",
                        "outcome":  "story.case_1057.choice.1",
                        "content":  "story.case_1057_b.0"
                    },
                    {
                        "type":  "tendency",
                        "key":  "justice",
                        "value":  3
                    },
                    {
                        "type":  "tendency",
                        "key":  "suspicion",
                        "value":  2
                    },
                    {
                        "type":  "corruption",
                        "value":  8
                    }
                ]
}
