{
  "id": "case_1045",
  "sfx": "Assets/audio/node_paper.wav",
  "text": [
    "story.case_1045.0",
    "story.case_1045.1",
    "story.case_1045.2",
    "story.case_1045.3",
    "story.case_1045.4"
  ],
  "choices": [
    {
      "text": "story.case_1045.choice.0",
      "next": "case_1045_a"
    },
    {
      "text": "story.case_1045.choice.1",
      "next": "case_1045_b"
    },
    {
      "text": "story.case_1045.choice.2",
      "next": "case_1045_c"
    },
    {
      "text": "story.case_1045.choice.3",
      "next": "case_1045_d",
      "require": [
        { "type": "flag", "key": "found_supply_cut" }
      ]
    }
  ]
}
