{
    "id":  "case_1044_e2",
    "text":  [
                 "story.case_1044_e2.0",
                 "story.case_1044_e2.1",
                 "story.case_1044_e2.2",
                 "story.case_1044_e2.3"
             ],
    "choices":  [
                    {
                        "text":  "story.common.next_case",
                        "next":  "day3_end_pending"
                    }
                ],
    "effects":  [
                    {
                        "type":  "case_record",
                        "key":  "case_1044",
                        "title":  "story.case_1044.0",
                        "outcome":  "story.case_1044_e.choice.1",
                        "content":  "story.case_1044_e2.0"
                    },
                    {
                        "type":  "tendency",
                        "key":  "justice",
                        "value":  2
                    },
                    {
                        "type":  "tendency",
                        "key":  "suspicion",
                        "value":  3
                    },
                    {
                        "type":  "corruption",
                        "value":  5
                    },
                    {
                        "type":  "flag_add",
                        "key":  "case_pending"
                    }
                ]
}
